LICENSE.txt
README.md
setup.py
pycodigof/__init__.py
pycodigof/__main__.py
pycodigof/articles.py
pycodigof/workshops.py
pycodigof.egg-info/PKG-INFO
pycodigof.egg-info/SOURCES.txt
pycodigof.egg-info/dependency_links.txt
pycodigof.egg-info/entry_points.txt
pycodigof.egg-info/requires.txt
pycodigof.egg-info/top_level.txt