Metadata-Version: 2.1
Name: pycodigof
Version: 0.0.4
Summary: This package allows you to consume the EndPoint of CodigoFacilito workshops and articles.
Home-page: https://github.com/HazaelJDev/python_package
Author: Hazael Jiménez
Author-email: jejibarrera@gmail.com
License: MIT
Keywords: codigofacilito
Platform: UNKNOWN
Classifier: Development Status :: 3 - Alpha
Classifier: Intended Audience :: Developers
Classifier: Topic :: Software Development :: Build Tools
Classifier: License :: OSI Approved :: MIT License
Classifier: Programming Language :: Python :: 3
License-File: LICENSE.txt
